new_my_json
