Metadata-Version: 1.1
Name: new-my-json
Version: 1.0.1
Summary: convert all the data to json
Home-page: UNKNOWN
Author: Animesh Kumar Jha
Author-email: animesh-kumar.jha@ucdconnect.ie
License: LICENSE.txt
Platform: UNKNOWN
Classifier: Development Status :: 3 - Alpha
Classifier: Intended Audience :: Developers
Classifier: Topic :: Software Development :: Build Tools
Classifier: Programming Language :: Python :: 3.4
Classifier: Programming Language :: Python :: 3.5
